captain_arro/__init__.py
captain_arro/constants.py
captain_arro/py.typed
captain_arro/generators/__init__.py
captain_arro/generators/base.py
captain_arro/generators/flow/__init__.py
captain_arro/generators/flow/moving_flow_arrow_generator.py
captain_arro/generators/flow/spotlight_flow_arrow_generator.py
captain_arro/generators/spread/__init__.py
captain_arro/generators/spread/bouncing_spread_arrow_generator.py
captain_arro/generators/spread/spotlight_spread_arrow_generator.py
captain_arro-0.1.1.dist-info/licenses/LICENSE
captain_arro-0.1.1.dist-info/METADATA
captain_arro-0.1.1.dist-info/WHEEL
captain_arro-0.1.1.dist-info/top_level.txt
captain_arro-0.1.1.dist-info/RECORD
