Metadata-Version: 2.4
Name: captain-arro
Version: 0.1.1
Summary: Animated SVG arrow generators for web interfaces
Author: Helge Esch
Maintainer: Helge Esch
License-Expression: MIT
Project-URL: Homepage, https://github.com/helgeesch/captain-arro
Project-URL: Repository, https://github.com/helgeesch/captain-arro
Project-URL: Documentation, https://github.com/helgeesch/captain-arro#readme
Project-URL: Bug Tracker, https://github.com/helgeesch/captain-arro/issues
Keywords: svg,animation,arrows,graphics,web,ui
Classifier: Development Status :: 4 - Beta
Classifier: Intended Audience :: Developers
Classifier: Programming Language :: Python :: 3
Classifier: Programming Language :: Python :: 3.8
Classifier: Programming Language :: Python :: 3.9
Classifier: Programming Language :: Python :: 3.10
Classifier: Programming Language :: Python :: 3.11
Classifier: Programming Language :: Python :: 3.12
Classifier: Topic :: Multimedia :: Graphics
Classifier: Topic :: Software Development :: Libraries :: Python Modules
Classifier: Topic :: Text Processing :: Markup :: HTML
Requires-Python: >=3.8
License-File: LICENSE
Provides-Extra: dev
Requires-Dist: pytest>=7.0; extra == "dev"
Requires-Dist: pytest-cov>=4.0; extra == "dev"
Requires-Dist: black>=23.0; extra == "dev"
Requires-Dist: isort>=5.0; extra == "dev"
Requires-Dist: mypy>=1.0; extra == "dev"
Requires-Dist: flake8>=6.0; extra == "dev"
Dynamic: license-file
